{
  "totalAdjustments": 9,
  "statusBreakdown": {
    "DRAFT": 9
  },
  "recentAdjustments": [
    {
      "adjustmentNumber": "ADJ-20251224-0009",
      "status": "DRAFT",
      "date": "2025-12-24"
    },
    {
      "adjustmentNumber": "ADJ-20251224-0008",
      "status": "DRAFT",
      "date": "2025-12-24"
    },
    {
      "adjustmentNumber": "ADJ-20251224-0007",
      "status": "DRAFT",
      "date": "2025-12-24"
    },
    {
      "adjustmentNumber": "ADJ-20251224-0006",
      "status": "DRAFT",
      "date": "2025-12-24"
    },
    {
      "adjustmentNumber": "ADJ-20251224-0005",
      "status": "DRAFT",
      "date": "2025-12-24"
    },
    {
      "adjustmentNumber": "ADJ-20251224-0004",
      "status": "DRAFT",
      "date": "2025-12-24"
    },
    {
      "adjustmentNumber": "ADJ-20251224-0003",
      "status": "DRAFT",
      "date": "2025-12-24"
    },
    {
      "adjustmentNumber": "ADJ-20251224-0002",
      "status": "DRAFT",
      "date": "2025-12-24"
    },
    {
      "adjustmentNumber": "ADJ-20251224-0001",
      "status": "DRAFT",
      "date": "2025-12-24"
    }
  ]
}