[
  {
    "id": "cmi8yksb3000svatgm14qoeqx",
    "name": "Manila Electric Company (MERALCO)",
    "contactPerson": "Customer Service",
    "phone": "16211",
    "email": "customercare@meralco.com.ph",
    "status": "active",
    "displayOrder": 1,
    "usageCount": 0,
    "createdAt": "2025-11-21T06:31:38.319Z",
    "updatedAt": "2025-12-02T17:55:02.498Z"
  },
  {
    "id": "cmi8yksrb000tvatg6mcvlbkv",
    "name": "Maynilad Water Services",
    "contactPerson": "Customer Service",
    "phone": "1626",
    "email": "customercare@mayniladwater.com.ph",
    "status": "active",
    "displayOrder": 2,
    "usageCount": 0,
    "createdAt": "2025-11-21T06:31:38.904Z",
    "updatedAt": "2025-12-02T17:55:02.568Z"
  },
  {
    "id": "cmi8ykt1c000uvatg2u418tw8",
    "name": "PLDT",
    "contactPerson": "Business Support",
    "phone": "171",
    "email": "business@pldt.com.ph",
    "status": "active",
    "displayOrder": 3,
    "usageCount": 0,
    "createdAt": "2025-11-21T06:31:39.265Z",
    "updatedAt": "2025-12-02T17:55:02.633Z"
  },
  {
    "id": "cmi8yktbe000vvatgqirf8vmw",
    "name": "Petron Corporation",
    "contactPerson": "Sales",
    "phone": "(02) 8884-9200",
    "email": null,
    "status": "active",
    "displayOrder": 4,
    "usageCount": 0,
    "createdAt": "2025-11-21T06:31:39.626Z",
    "updatedAt": "2025-12-02T17:55:02.699Z"
  },
  {
    "id": "cmi8yktnf000wvatgukm05nfw",
    "name": "Shell Philippines",
    "contactPerson": "Fleet Card Services",
    "phone": "1-800-10-888-7435",
    "email": null,
    "status": "active",
    "displayOrder": 5,
    "usageCount": 0,
    "createdAt": "2025-11-21T06:31:40.059Z",
    "updatedAt": "2025-12-02T17:55:02.765Z"
  }
]